ChangeLog
LICENSE.txt
README.txt
TODO
setup.py
py_1digit_checksum/.verhoeff.txt.swp
py_1digit_checksum/__init__.py
py_1digit_checksum/test.py
py_1digit_checksum/verhoeff.py
py_1digit_checksum/verhoeff.txt
py_1digit_checksum.egg-info/PKG-INFO
py_1digit_checksum.egg-info/SOURCES.txt
py_1digit_checksum.egg-info/dependency_links.txt
py_1digit_checksum.egg-info/top_level.txt