Metadata-Version: 1.0
Name: py-1digit-checksum
Version: 0.0.1
Summary: Several 1-digit checksum algorithms
Home-page: UNKNOWN
Author: Hermann Himmelbauer
Author-email: hermann@qwer.tk
License: LGPL
Platform: UNKNOWN
